ansible_vault/__init__.py
ansible_vault/api.py
ansible_vault/parsing.py
ansible_vault-4.1.0.dist-info/licenses/LICENSE.txt
ansible_vault-4.1.0.dist-info/METADATA
ansible_vault-4.1.0.dist-info/WHEEL
ansible_vault-4.1.0.dist-info/top_level.txt
ansible_vault-4.1.0.dist-info/RECORD
