Metadata-Version: 2.4
Name: ansible-vault
Version: 4.1.0
Summary: R/W an ansible-vault yaml file
Home-page: https://github.com/tomoh1r/ansible-vault
Author: Tomohiro NAKAMURA
Author-email: quickness.net@gmail.com
License: GPL-3.0-or-later
Classifier: Programming Language :: Python :: 3.10
Classifier: Programming Language :: Python :: 3.11
Classifier: Programming Language :: Python :: 3.12
Classifier: Programming Language :: Python :: 3.13
Classifier: Development Status :: 5 - Production/Stable
License-File: LICENSE.txt
Requires-Dist: ansible-core>=2.16
Requires-Dist: PyYAML>=5.1
Provides-Extra: dev
Requires-Dist: setuptools; extra == "dev"
Requires-Dist: pytest; extra == "dev"
Requires-Dist: pytest-cov; extra == "dev"
Requires-Dist: coveralls; extra == "dev"
Requires-Dist: flake8; extra == "dev"
Requires-Dist: black; extra == "dev"
Requires-Dist: isort; extra == "dev"
Requires-Dist: pylint; extra == "dev"
Requires-Dist: pylint-pytest; extra == "dev"
Provides-Extra: release
Requires-Dist: build; extra == "release"
Requires-Dist: twine; extra == "release"
Dynamic: author
Dynamic: author-email
Dynamic: classifier
Dynamic: description
Dynamic: description-content-type
Dynamic: home-page
Dynamic: license
Dynamic: license-file
Dynamic: provides-extra
Dynamic: requires-dist
Dynamic: summary
